carbonara_cli/__init__.py
carbonara_cli/__main__.py
carbonara_cli/main.py
carbonara_cli-1.0.13.dist-info/DESCRIPTION.rst
carbonara_cli-1.0.13.dist-info/METADATA
carbonara_cli-1.0.13.dist-info/RECORD
carbonara_cli-1.0.13.dist-info/WHEEL
carbonara_cli-1.0.13.dist-info/entry_points.txt
carbonara_cli-1.0.13.dist-info/metadata.json
carbonara_cli-1.0.13.dist-info/top_level.txt
