Metadata-Version: 2.0
Name: carbonara-cli
Version: 1.0.13
Summary: CLI interface for Carbonara
Home-page: https://github.com/Carbonara-Project/Carbonara-CLI
Author: Andrea Fioraldi, Luigi Paolo Pileggi
Author-email: andreafioraldi@gmail.com, willownoises@gmail.com
License: BSD 2-clause
Download-URL: https://github.com/Carbonara-Project/Carbonara-CLI/archive/1.0.13.tar.gz
Platform: UNKNOWN
Requires-Dist: progressbar2
Requires-Dist: guanciale
